bewegung/__init__.py
bewegung/animation/__init__.py
bewegung/animation/_abc.py
bewegung/animation/_const.py
bewegung/animation/_effects.py
bewegung/animation/_encoders.py
bewegung/animation/_indexpool.py
bewegung/animation/_layer.py
bewegung/animation/_sequence.py
bewegung/animation/_task.py
bewegung/animation/_time.py
bewegung/animation/_timescale.py
bewegung/animation/_video.py
bewegung/animation/_backends/__init__.py
bewegung/animation/_backends/_base.py
bewegung/animation/_backends/_load.py
bewegung/animation/_backends/cairo.py
bewegung/animation/_backends/datashader.py
bewegung/animation/_backends/drawingboard.py
bewegung/animation/_backends/matplotlib.py
bewegung/animation/_backends/pillow.py
bewegung/contrib/__init__.py
bewegung/contrib/circular_century_calendar.py
bewegung/drawingboard/__init__.py
bewegung/drawingboard/_abc.py
bewegung/drawingboard/_core.py
bewegung/lib/__init__.py
bewegung/lib/_abc.py
bewegung/lib/_color.py
bewegung/lib/_typeguard.py
bewegung/linalg/__init__.py
bewegung/linalg/_abc.py
bewegung/linalg/_array.py
bewegung/linalg/_array2d.py
bewegung/linalg/_array3d.py
bewegung/linalg/_camera.py
bewegung/linalg/_const.py
bewegung/linalg/_lib.py
bewegung/linalg/_matrix.py
bewegung/linalg/_matrixarray.py
bewegung/linalg/_numpy.py
bewegung/linalg/_single.py
bewegung/linalg/_single2d.py
bewegung/linalg/_single3d.py
bewegung/linalg/_svg.py
bewegung-0.0.7.dist-info/LICENSE
bewegung-0.0.7.dist-info/METADATA
bewegung-0.0.7.dist-info/WHEEL
bewegung-0.0.7.dist-info/top_level.txt
bewegung-0.0.7.dist-info/RECORD
