Metadata-Version: 2.1
Name: bewegung
Version: 0.0.7
Summary: a versatile video renderer
Home-page: https://github.com/pleiszenburg/bewegung
Author: Sebastian M. Ernst
Author-email: ernst@pleiszenburg.de
License: LGPLv2
Download-URL: https://github.com/pleiszenburg/bewegung/archive/v0.0.7.tar.gz
Keywords: video,animation,animation-framework,rendering,rendering,rendering-engine,compositor
Platform: UNKNOWN
Classifier: Development Status :: 3 - Alpha
Classifier: Intended Audience :: Developers
Classifier: Intended Audience :: Education
Classifier: Intended Audience :: Financial and Insurance Industry
Classifier: Intended Audience :: Healthcare Industry
Classifier: Intended Audience :: Science/Research
Classifier: License :: OSI Approved :: GNU Lesser General Public License v2 (LGPLv2)
Classifier: Operating System :: MacOS
Classifier: Operating System :: POSIX :: BSD
Classifier: Operating System :: POSIX :: Linux
Classifier: Programming Language :: Python :: 3
Classifier: Programming Language :: Python :: 3.6
Classifier: Programming Language :: Python :: 3.7
Classifier: Programming Language :: Python :: 3.8
Classifier: Programming Language :: Python :: 3.9
Classifier: Programming Language :: Python :: 3 :: Only
Classifier: Programming Language :: Python :: Implementation :: CPython
Classifier: Topic :: Artistic Software
Classifier: Topic :: Education
Classifier: Topic :: Multimedia
Classifier: Topic :: Multimedia :: Graphics
Classifier: Topic :: Multimedia :: Graphics :: Presentation
Classifier: Topic :: Multimedia :: Sound/Audio
Classifier: Topic :: Multimedia :: Sound/Audio :: Editors
Classifier: Topic :: Multimedia :: Sound/Audio :: Mixers
Classifier: Topic :: Multimedia :: Video
Classifier: Topic :: Scientific/Engineering
Classifier: Topic :: Scientific/Engineering :: Visualization
Classifier: Topic :: Software Development :: Libraries
Requires-Python: >=3.6
License-File: LICENSE
Requires-Dist: Pillow
Provides-Extra: all
Requires-Dist: python-lsp-server[all] ; extra == 'all'
Requires-Dist: twine ; extra == 'all'
Requires-Dist: numba ; extra == 'all'
Requires-Dist: PyGObject ; extra == 'all'
Requires-Dist: black ; extra == 'all'
Requires-Dist: sphinx-autodoc-typehints ; extra == 'all'
Requires-Dist: matplotlib ; extra == 'all'
Requires-Dist: pycairo ; extra == 'all'
Requires-Dist: sphinxembeddedvideos ; extra == 'all'
Requires-Dist: coverage ; extra == 'all'
Requires-Dist: setuptools ; extra == 'all'
Requires-Dist: typeguard ; extra == 'all'
Requires-Dist: psutil ; extra == 'all'
Requires-Dist: sphinx-rtd-theme ; extra == 'all'
Requires-Dist: myst-parser ; extra == 'all'
Requires-Dist: hypothesis ; extra == 'all'
Requires-Dist: Sphinx ; extra == 'all'
Requires-Dist: datashader ; extra == 'all'
Requires-Dist: mplcairo ; extra == 'all'
Requires-Dist: tqdm ; extra == 'all'
Requires-Dist: wheel ; extra == 'all'
Requires-Dist: numpy ; extra == 'all'
Requires-Dist: pytest ; extra == 'all'
Requires-Dist: ipython ; extra == 'all'
Requires-Dist: pytest-cov ; extra == 'all'
Provides-Extra: cairo
Requires-Dist: pycairo ; extra == 'cairo'
Provides-Extra: datashader
Requires-Dist: datashader ; extra == 'datashader'
Provides-Extra: dev
Requires-Dist: coverage ; extra == 'dev'
Requires-Dist: black ; extra == 'dev'
Requires-Dist: hypothesis ; extra == 'dev'
Requires-Dist: python-lsp-server[all] ; extra == 'dev'
Requires-Dist: psutil ; extra == 'dev'
Requires-Dist: setuptools ; extra == 'dev'
Requires-Dist: Sphinx ; extra == 'dev'
Requires-Dist: sphinx-autodoc-typehints ; extra == 'dev'
Requires-Dist: sphinx-rtd-theme ; extra == 'dev'
Requires-Dist: sphinxembeddedvideos ; extra == 'dev'
Requires-Dist: myst-parser ; extra == 'dev'
Requires-Dist: pytest ; extra == 'dev'
Requires-Dist: pytest-cov ; extra == 'dev'
Requires-Dist: twine ; extra == 'dev'
Requires-Dist: wheel ; extra == 'dev'
Provides-Extra: docs
Requires-Dist: python-lsp-server[all] ; extra == 'docs'
Requires-Dist: datashader ; extra == 'docs'
Requires-Dist: twine ; extra == 'docs'
Requires-Dist: numba ; extra == 'docs'
Requires-Dist: pytest-cov ; extra == 'docs'
Requires-Dist: mplcairo ; extra == 'docs'
Requires-Dist: black ; extra == 'docs'
Requires-Dist: tqdm ; extra == 'docs'
Requires-Dist: sphinx-autodoc-typehints ; extra == 'docs'
Requires-Dist: sphinx-rtd-theme ; extra == 'docs'
Requires-Dist: myst-parser ; extra == 'docs'
Requires-Dist: wheel ; extra == 'docs'
Requires-Dist: matplotlib ; extra == 'docs'
Requires-Dist: pycairo ; extra == 'docs'
Requires-Dist: sphinxembeddedvideos ; extra == 'docs'
Requires-Dist: coverage ; extra == 'docs'
Requires-Dist: numpy ; extra == 'docs'
Requires-Dist: setuptools ; extra == 'docs'
Requires-Dist: typeguard ; extra == 'docs'
Requires-Dist: pytest ; extra == 'docs'
Requires-Dist: psutil ; extra == 'docs'
Requires-Dist: ipython ; extra == 'docs'
Requires-Dist: hypothesis ; extra == 'docs'
Requires-Dist: Sphinx ; extra == 'docs'
Provides-Extra: drawingboard
Requires-Dist: pycairo ; extra == 'drawingboard'
Requires-Dist: PyGObject ; extra == 'drawingboard'
Provides-Extra: ipython
Requires-Dist: ipython ; extra == 'ipython'
Provides-Extra: matplotlib
Requires-Dist: numpy ; extra == 'matplotlib'
Requires-Dist: matplotlib ; extra == 'matplotlib'
Requires-Dist: pycairo ; extra == 'matplotlib'
Requires-Dist: mplcairo ; extra == 'matplotlib'
Provides-Extra: numba
Requires-Dist: numba ; extra == 'numba'
Provides-Extra: numpy
Requires-Dist: numpy ; extra == 'numpy'
Provides-Extra: tqdm
Requires-Dist: tqdm ; extra == 'tqdm'
Provides-Extra: typeguard
Requires-Dist: typeguard ; extra == 'typeguard'
